azure_databricks_api/__base.py
azure_databricks_api/__clusters.py
azure_databricks_api/__dbfs.py
azure_databricks_api/__groups.py
azure_databricks_api/__init__.py
azure_databricks_api/__jobs.py
azure_databricks_api/__libraries.py
azure_databricks_api/__rest_client.py
azure_databricks_api/__secrets.py
azure_databricks_api/__token.py
azure_databricks_api/__users.py
azure_databricks_api/__utils.py
azure_databricks_api/__workspace.py
azure_databricks_api/exceptions.py
azure_databricks_api-0.6.2.dist-info/AUTHORS
azure_databricks_api-0.6.2.dist-info/LICENSE
azure_databricks_api-0.6.2.dist-info/METADATA
azure_databricks_api-0.6.2.dist-info/WHEEL
azure_databricks_api-0.6.2.dist-info/pbr.json
azure_databricks_api-0.6.2.dist-info/top_level.txt
azure_databricks_api-0.6.2.dist-info/RECORD
