Metadata-Version: 2.1
Name: azure-databricks-api
Version: 0.6.2
Summary: A wrapper for the Azure Databricks REST API
Home-page: http://github.com/ezwiefel/azure-databricks-api
Author: Erik Zwiefel
Author-email: erikzw@outlook.com
Maintainer: Erik Zwiefel
Maintainer-email: erikzw@outlook.com
License: MIT
Keywords: azure,databricks
Platform: UNKNOWN
Classifier: Development Status :: 3 - Alpha
Classifier: Intended Audience :: Developers
Classifier: Intended Audience :: Information Technology
Classifier: License :: OSI Approved :: MIT License
Classifier: Operating System :: OS Independent
Classifier: Programming Language :: Python
Classifier: Programming Language :: Python :: 3
Classifier: Programming Language :: Python :: 3.6
Requires-Dist: requests (>=2.20.0)
